public_transit_viewer/__init__.py
public_transit_viewer/assets/__init__.py
public_transit_viewer/assets/favicon.ico
public_transit_viewer/assets/naviqore-round.png
public_transit_viewer/components/__init__.py
public_transit_viewer/components/form_components.py
public_transit_viewer/components/logo.py
public_transit_viewer/components/map.py
public_transit_viewer/connections.py
public_transit_viewer/entrypoint.py
public_transit_viewer/pages/__init__.py
public_transit_viewer/pages/isolines.py
public_transit_viewer/py.typed
public_transit_viewer/utils/__init__.py
public_transit_viewer/utils/client.py
public_transit_viewer/utils/color.py
public_transit_viewer/utils/connection.py
public_transit_viewer-1.0.0.dist-info/LICENSE
public_transit_viewer-1.0.0.dist-info/METADATA
public_transit_viewer-1.0.0.dist-info/WHEEL
public_transit_viewer-1.0.0.dist-info/entry_points.txt
public_transit_viewer-1.0.0.dist-info/RECORD
