Metadata-Version: 2.1
Name: public-transit-viewer
Version: 1.0.0
Summary: Viewer to interact with the public transit service.
Author: Lukas Connolly
Author-email: lukas@connolly.ch
Requires-Python: >=3.12,<4.0
Classifier: Programming Language :: Python :: 3
Classifier: Programming Language :: Python :: 3.12
Requires-Dist: folium (>=0.17.0,<0.18.0)
Requires-Dist: matplotlib (>=3.9.2,<4.0.0)
Requires-Dist: pandas (>=2.2.2,<3.0.0)
Requires-Dist: public-transit-client (>=1.0.0,<2.0.0)
Requires-Dist: pydantic (>=2.8.2,<3.0.0)
Requires-Dist: python-dotenv (>=1.0.1,<2.0.0)
Requires-Dist: streamlit (>=1.34,<1.35)
Requires-Dist: streamlit-searchbox (>=0.1.14,<0.2.0)
Requires-Dist: watchdog (>=4.0.2,<6.0.0)
